grimoire_mordred-0.1.29.data/scripts/mordred
grimoire_mordred-0.1.29.dist-info/METADATA
grimoire_mordred-0.1.29.dist-info/RECORD
grimoire_mordred-0.1.29.dist-info/WHEEL
grimoire_mordred-0.1.29.dist-info/top_level.txt
mordred/__init__.py
mordred/_version.py
mordred/config.py
mordred/eclipse_projects_lib.py
mordred/error.py
mordred/github.py
mordred/mordred.py
mordred/task.py
mordred/task_collection.py
mordred/task_enrich.py
mordred/task_identities.py
mordred/task_manager.py
mordred/task_panels.py
mordred/task_projects.py
mordred/task_report.py
mordred/task_track.py
