Metadata-Version: 2.1
Name: grimoire-mordred
Version: 0.1.29
Summary: Drive GrimoireLab tools to produce a dashboard
Home-page: https://github.com/grimoirelab/mordred
Author: CHAOSS
Author-email: acs@bitergia.com
License: GPLv3
Keywords: development repositories analytics git github bugzilla jira jenkins
Platform: UNKNOWN
Classifier: Development Status :: 5 - Production/Stable
Classifier: Intended Audience :: Developers
Classifier: Topic :: Software Development
Classifier: License :: OSI Approved :: GNU General Public License v3 or later (GPLv3+)
Classifier: Programming Language :: Python :: 3
Requires-Dist: grimoire-elk (>=0.30.33)
Requires-Dist: kidash (>=0.4.4)
Requires-Dist: manuscripts (>=0.2.7)
Requires-Dist: sortinghat (>=0.6.2)
Requires-Dist: PyMySQL
Requires-Dist: pyyaml
Requires-Dist: redis
Requires-Dist: kingarthur (>=0.1.7)
